weaver/__init__.py
weaver/datasets.py
weaver/optimizers.py
weaver/schedulers.py
weaver/classifiers/__init__.py
weaver/classifiers/resnets.py
weaver/classifiers/custom/__init__.py
weaver/classifiers/custom/prn18.py
weaver/classifiers/custom/wrn28.py
weaver/transforms/__init__.py
weaver/transforms/custom/__init__.py
weaver/transforms/custom/all_rand_augment.py
weaver/transforms/custom/functional.py
weaver/transforms/custom/transforms.py
weaver_pytorch_rnx0dvmdxk-0.0.4.dist-info/LICENSE
weaver_pytorch_rnx0dvmdxk-0.0.4.dist-info/METADATA
weaver_pytorch_rnx0dvmdxk-0.0.4.dist-info/WHEEL
weaver_pytorch_rnx0dvmdxk-0.0.4.dist-info/top_level.txt
weaver_pytorch_rnx0dvmdxk-0.0.4.dist-info/RECORD
