Metadata-Version: 2.1
Name: weaver-pytorch-rnx0dvmdxk
Version: 0.0.4
Summary: Small utilities for PyTorch
Home-page: https://github.com/Holim0711/Weaver
Author: Holim Lim
Author-email: ihl7029@europa.snu.ac.kr
Classifier: Programming Language :: Python :: 3
Classifier: License :: OSI Approved :: MIT License
Classifier: Operating System :: OS Independent
Requires-Python: >=3.8
License-File: LICENSE
